named_sequence/__init__.py
named_sequence/named_sequence.py
named_sequence-1.0.dist-info/METADATA
named_sequence-1.0.dist-info/WHEEL
named_sequence-1.0.dist-info/top_level.txt
named_sequence-1.0.dist-info/RECORD
