Metadata-Version: 2.1
Name: named-sequence
Version: 1.0
Summary: list like object allowing selection by name and index
Author: Marc MALBERT
Author-email: eldrad-59@hotmail.fr
Classifier: Programming Language :: Python :: 3
Classifier: Development Status :: 5 - Production/Stable
Classifier: Natural Language :: English
Classifier: Operating System :: OS Independent
